pdf_chunker/__init__.py
pdf_chunker/chunker.py
pdf_chunker-0.1.1.dist-info/LICENSE
pdf_chunker-0.1.1.dist-info/METADATA
pdf_chunker-0.1.1.dist-info/WHEEL
pdf_chunker-0.1.1.dist-info/top_level.txt
pdf_chunker-0.1.1.dist-info/RECORD
